LICENSE
README.md
setup.py
google_search_result_scraper/__init__.py
google_search_result_scraper.egg-info/PKG-INFO
google_search_result_scraper.egg-info/SOURCES.txt
google_search_result_scraper.egg-info/dependency_links.txt
google_search_result_scraper.egg-info/requires.txt
google_search_result_scraper.egg-info/top_level.txt